pycba/__init__.py
pycba/analysis.py
pycba/beam.py
pycba/bridge.py
pycba/inf_lines.py
pycba/load.py
pycba/pattern.py
pycba/results.py
pycba/utils.py
pycba/vehicle.py
PyCBA-0.5.2.dist-info/LICENSE
PyCBA-0.5.2.dist-info/METADATA
PyCBA-0.5.2.dist-info/WHEEL
PyCBA-0.5.2.dist-info/top_level.txt
PyCBA-0.5.2.dist-info/RECORD
