Metadata-Version: 2.1
Name: PyCBA
Version: 0.5.2
Summary: Python Continuous Beam Analysis
Author-email: Colin Caprani <colin.caprani@monash.edu>
License: Apache 2.0
Project-URL: Homepage, https://ccaprani.github.io/pycba/
Project-URL: Documentation, https://ccaprani.github.io/pycba/
Project-URL: Source, https://github.com/ccaprani/pycba/
Project-URL: Tracker, https://github.com/ccaprani/pycba/issues/
Keywords: beam,bridge,vehicle
Platform: any
Classifier: Development Status :: 4 - Beta
Classifier: Topic :: Scientific/Engineering
Classifier: Environment :: Console
Classifier: Intended Audience :: Science/Research
Classifier: Programming Language :: Python :: 3 :: Only
Classifier: License :: OSI Approved :: Apache Software License
Classifier: Natural Language :: English
Classifier: Operating System :: POSIX :: Linux
Classifier: Operating System :: MacOS :: MacOS X
Classifier: Operating System :: Microsoft :: Windows
Classifier: Programming Language :: Python :: 3.8
Classifier: Programming Language :: Python :: 3.9
Classifier: Programming Language :: Python :: 3.10
Classifier: Programming Language :: Python :: 3.11
Requires-Python: >=3.8
License-File: LICENSE
Requires-Dist: matplotlib
Requires-Dist: numpy
Requires-Dist: scipy >=1.6.0
Provides-Extra: test
Requires-Dist: pytest >=6.2.2 ; extra == 'test'
